{
  "meta": {
    "desc": "OpenSimplex Noise functions for 2D, 3D and 4D",
    "desc_long": "OpenSimplex noise is an n-dimensional gradient noise function that was\ndeveloped in order to overcome the patent-related issues surrounding\nSimplex noise, while continuing to also avoid the visually-significant\ndirectional artifacts characteristic of Perlin noise.\n",
    "home": "https://github.com/lmas/opensimplex",
    "license": [
      {
        "deprecated": false,
        "free": true,
        "fullName": "MIT License",
        "redistributable": true,
        "shortName": "mit",
        "spdxId": "MIT",
        "url": "https://spdx.org/licenses/MIT.html"
      }
    ],
    "maintainers": [
      {
        "email": "nix@angus.ws",
        "github": "angustrau",
        "githubId": 13267947,
        "matrix": "@angustrau:matrix.org",
        "name": "Angus Trau"
      }
    ]
  },
  "versions": [
    {
      "commits": [
        {
          "first": "0025dce444f2f8fdfff6c6ca6b9cc9cb06f6688e",
          "last": "0031ccab55e72a1ca59128882f9f98de2a049226"
        }
      ],
      "name": "0.4.2"
    },
    {
      "commits": [
        {
          "first": "002467e0d628501f5762602bef3ba9fa36a00228",
          "last": "002467e0d628501f5762602bef3ba9fa36a00228"
        }
      ],
      "name": "0.4"
    },
    {
      "commits": [
        {
          "first": "032bd9e92db705ec95f233732dcdba712c17ee02",
          "last": "0022c16ae5a9706ed77c94bdd3da94d57a9a1843"
        }
      ],
      "name": "0.3"
    }
  ]
}