{
  "meta": {
    "desc": "Prometheus instrumentation library for Python applications",
    "desc_long": null,
    "home": "https://github.com/prometheus/client_python",
    "license": {
      "deprecated": false,
      "free": true,
      "fullName": "Apache License 2.0",
      "redistributable": true,
      "shortName": "asl20",
      "spdxId": "Apache-2.0",
      "url": "https://spdx.org/licenses/Apache-2.0.html"
    },
    "maintainers": null
  },
  "versions": [
    {
      "commits": [
        {
          "first": "0036078a21f199a0a17e4a0e66928986fd52cf26",
          "last": "0031ccab55e72a1ca59128882f9f98de2a049226"
        }
      ],
      "name": "0.14.1"
    },
    {
      "commits": [
        {
          "first": "00154ce2689a5affe0320c49e8b300cf9113447e",
          "last": "00004be60ea161a1a30f3b32d33cb3d43cd88d32"
        }
      ],
      "name": "0.13.1"
    },
    {
      "commits": [
        {
          "first": "0028d75b1c912e4bcbae870e40ee8fd553f32a17",
          "last": "0018daf5b9c4bbe67253c903b414e41b4f89eb31"
        }
      ],
      "name": "0.12.0"
    },
    {
      "commits": [
        {
          "first": "034b80b453147efcabc75976700d51807e16759f",
          "last": "001c75d537c959f028229f33803a8c15b142613b"
        }
      ],
      "name": "0.11.0"
    }
  ]
}